actions_server/__init__.py
actions_server/example.py
actions_server/server.py
actions_server/test_server.py
actions_server/test_server_blocking.py
actions_server-0.0.10.dist-info/LICENSE
actions_server-0.0.10.dist-info/METADATA
actions_server-0.0.10.dist-info/WHEEL
actions_server-0.0.10.dist-info/top_level.txt
actions_server-0.0.10.dist-info/RECORD
