Metadata-Version: 2.1
Name: actions-server
Version: 0.0.10
Summary: A very simple, multi-threaded HTTP server
Home-page: https://github.com/rzarajczyk/actions-server
Author: Rafał Zarajczyk
Author-email: rzarajczyk@gmail.com
Keywords: HTTP,SERVER
Classifier: Programming Language :: Python :: 3
Classifier: License :: OSI Approved :: MIT License
Classifier: Operating System :: OS Independent
License-File: LICENSE
Requires-Dist: requests >=2.31.0
Requires-Dist: multipart >=0.2.4
Requires-Dist: deser >=0.0.1
